asynctor-0.12.2.dist-info/METADATA
asynctor-0.12.2.dist-info/WHEEL
asynctor-0.12.2.dist-info/entry_points.txt
asynctor-0.12.2.dist-info/licenses/LICENSE
asynctor/__init__.py
asynctor/aio.py
asynctor/client.py
asynctor/compat.py
asynctor/contrib/__init__.py
asynctor/contrib/fastapi.py
asynctor/enums.py
asynctor/exceptions.py
asynctor/jsons.py
asynctor/py.typed
asynctor/tasks.py
asynctor/testing.py
asynctor/timing.py
asynctor/utils.py
asynctor/xls.py
asynctor/xlsx.py
asynctor-0.12.2.dist-info/RECORD
