Metadata-Version: 2.1
Name: asynctor
Version: 0.12.2
Summary: Async functions to compare with anyio and asyncio, and toolkit to read excel with async/await.
Keywords: asyncio,anyio,aioredis
Author-Email: Waket Zheng <waketzheng@gmail.com>
License: MIT
Classifier: Development Status :: 4 - Beta
Classifier: Intended Audience :: Developers
Classifier: License :: OSI Approved :: MIT License
Classifier: Operating System :: OS Independent
Classifier: Typing :: Typed
Classifier: Programming Language :: Python :: 3
Classifier: Programming Language :: Python :: 3.10
Classifier: Programming Language :: Python :: 3.11
Classifier: Programming Language :: Python :: 3.12
Classifier: Programming Language :: Python :: 3.13
Classifier: Programming Language :: Python :: 3.14
Project-URL: homepage, https://github.com/waketzheng/asynctor
Project-URL: repository, https://github.com/waketzheng/asynctor.git
Project-URL: Bug Tracker, https://github.com/waketzheng/asynctor/issues
Requires-Python: >=3.10
Requires-Dist: anyio>=3.7.1
Requires-Dist: eval-type-backport<1.0.0,>=0.2.2; python_version < "3.10"
Provides-Extra: toml
Requires-Dist: tomli>=2.2.1; python_version < "3.11" and extra == "toml"
Provides-Extra: redis
Requires-Dist: redis>=5.0.0; extra == "redis"
Provides-Extra: xlsx
Requires-Dist: pandas>=2.2.0; extra == "xlsx"
Requires-Dist: openpyxl>=3.1.0; extra == "xlsx"
Provides-Extra: testing
Requires-Dist: httpx>=0.28.1; extra == "testing"
Requires-Dist: asgi-lifespan>=2.1.0; extra == "testing"
Provides-Extra: fastapi
Requires-Dist: asynctor[redis,testing]; extra == "fastapi"
Requires-Dist: fastapi>=0.115.0; extra == "fastapi"
Provides-Extra: tomli
Requires-Dist: asynctor[toml]; extra == "tomli"
Provides-Extra: xls
Requires-Dist: asynctor[xlsx]; extra == "xls"
Provides-Extra: all
Requires-Dist: asynctor[fastapi,redis,testing,toml,xlsx]; extra == "all"
